funcs_aux/__init__.py
funcs_aux/args.py
funcs_aux/arrays.py
funcs_aux/breeder_objects.py
funcs_aux/breeder_str_series.py
funcs_aux/breeder_str_stack.py
funcs_aux/ensure.py
funcs_aux/iterables.py
funcs_aux/result_cum.py
funcs_aux/static.py
funcs_aux/strings.py
funcs_aux/valid.py
funcs_aux/valid_aux.py
funcs_aux/valid_derivatives.py
funcs_aux/valid_regexp.py
funcs_aux/value_explicit.py
funcs_aux/value_unit.py
funcs_aux/value_variants.py
funcs_aux-0.4.38.dist-info/LICENSE
funcs_aux-0.4.38.dist-info/METADATA
funcs_aux-0.4.38.dist-info/WHEEL
funcs_aux-0.4.38.dist-info/top_level.txt
funcs_aux-0.4.38.dist-info/RECORD
